{
  "_links": {
    "self": {
      "href": "https://us.api.blizzard.com/data/wow/connected-realm/4648/mythic-leaderboard/56/period/1023?namespace=dynamic-classic-us"
    }
  },
  "map": {
    "name": {
      "en_US": "Stormstout Brewery",
      "es_MX": "Cervecer\u00eda del Trueno",
      "pt_BR": "Cervejaria Malte do Trov\u00e3o",
      "de_DE": "Brauerei Sturmbr\u00e4u",
      "en_GB": "Stormstout Brewery",
      "es_ES": "Cervecer\u00eda del Trueno",
      "fr_FR": "Brasserie Brune d\u2019Orage",
      "it_IT": "Birrificio Triplo Malto",
      "ru_RU": "\u0425\u043c\u0435\u043b\u0435\u0432\u0430\u0440\u043d\u044f \u0411\u0443\u0439\u043d\u044b\u0445 \u041f\u043e\u0440\u0442\u0435\u0440\u043e\u0432",
      "ko_KR": "\uc2a4\ud1b0\uc2a4\ud0c0\uc6b0\ud2b8 \uc591\uc870\uc7a5",
      "zh_TW": "\u98a8\u66b4\u70c8\u9152\u9152\u574a",
      "zh_CN": "\u98ce\u66b4\u70c8\u9152\u917f\u9020\u5382"
    },
    "id": 961
  },
  "period": 1023,
  "period_start_timestamp": 1754406000000,
  "period_end_timestamp": 1755010799000,
  "connected_realm": {
    "href": "https://us.api.blizzard.com/data/wow/connected-realm/4648?namespace=dynamic-classic-us"
  },
  "leading_groups": [
    {
      "ranking": 1,
      "duration": 652566,
      "completed_timestamp": 1753856877000,
      "keystone_level": 1,
      "members": [
        {
          "profile": {
            "name": "Hokoshi",
            "id": 61113246,
            "realm": {
              "key": {
                "href": "https://us.api.blizzard.com/data/wow/realm/4648?namespace=dynamic-classic-us"
              },
              "id": 4648,
              "slug": "bloodsail-buccaneers"
            }
          },
          "faction": {
            "type": "ALLIANCE"
          },
          "specialization": {
            "key": {
              "href": "https://us.api.blizzard.com/data/wow/playable-specialization/71?namespace=static-5.5.0_61496-classic-us"
            },
            "id": 71
          }
        },
        {
          "profile": {
            "name": "Raan",
            "id": 12876152,
            "realm": {
              "key": {
                "href": "https://us.api.blizzard.com/data/wow/realm/4648?namespace=dynamic-classic-us"
              },
              "id": 4648,
              "slug": "bloodsail-buccaneers"
            }
          },
          "faction": {
            "type": "ALLIANCE"
          },
          "specialization": {
            "key": {
              "href": "https://us.api.blizzard.com/data/wow/playable-specialization/255?namespace=static-5.5.0_61496-classic-us"
            },
            "id": 255
          }
        },
        {
          "profile": {
            "name": "Erusian",
            "id": 74898677,
            "realm": {
              "key": {
                "href": "https://us.api.blizzard.com/data/wow/realm/4648?namespace=dynamic-classic-us"
              },
              "id": 4648,
              "slug": "bloodsail-buccaneers"
            }
          },
          "faction": {
            "type": "ALLIANCE"
          },
          "specialization": {
            "key": {
              "href": "https://us.api.blizzard.com/data/wow/playable-specialization/250?namespace=static-5.5.0_61496-classic-us"
            },
            "id": 250
          }
        },
        {
          "profile": {
            "name": "Sashime",
            "id": 54394727,
            "realm": {
              "key": {
                "href": "https://us.api.blizzard.com/data/wow/realm/4648?namespace=dynamic-classic-us"
              },
              "id": 4648,
              "slug": "bloodsail-buccaneers"
            }
          },
          "faction": {
            "type": "ALLIANCE"
          },
          "specialization": {
            "key": {
              "href": "https://us.api.blizzard.com/data/wow/playable-specialization/256?namespace=static-5.5.0_61496-classic-us"
            },
            "id": 256
          }
        },
        {
          "profile": {
            "name": "Manubrius",
            "id": 48409732,
            "realm": {
              "key": {
                "href": "https://us.api.blizzard.com/data/wow/realm/4648?namespace=dynamic-classic-us"
              },
              "id": 4648,
              "slug": "bloodsail-buccaneers"
            }
          },
          "faction": {
            "type": "ALLIANCE"
          },
          "specialization": {
            "key": {
              "href": "https://us.api.blizzard.com/data/wow/playable-specialization/261?namespace=static-5.5.0_61496-classic-us"
            },
            "id": 261
          }
        }
      ],
      "mythic_rating": {
        "rating": 30.0
      }
    },
    {
      "ranking": 2,
      "duration": 1192944,
      "completed_timestamp": 1753839751000,
      "keystone_level": 1,
      "members": [
        {
          "profile": {
            "name": "Lizardsting",
            "id": 89775269,
            "realm": {
              "key": {
                "href": "https://us.api.blizzard.com/data/wow/realm/4648?namespace=dynamic-classic-us"
              },
              "id": 4648,
              "slug": "bloodsail-buccaneers"
            }
          },
          "faction": {
            "type": "ALLIANCE"
          },
          "specialization": {
            "key": {
              "href": "https://us.api.blizzard.com/data/wow/playable-specialization/255?namespace=static-5.5.0_61496-classic-us"
            },
            "id": 255
          }
        },
        {
          "profile": {
            "name": "Totallymax",
            "id": 13111654,
            "realm": {
              "key": {
                "href": "https://us.api.blizzard.com/data/wow/realm/4648?namespace=dynamic-classic-us"
              },
              "id": 4648,
              "slug": "bloodsail-buccaneers"
            }
          },
          "faction": {
            "type": "ALLIANCE"
          },
          "specialization": {
            "key": {
              "href": "https://us.api.blizzard.com/data/wow/playable-specialization/103?namespace=static-5.5.0_61496-classic-us"
            },
            "id": 103
          }
        },
        {
          "profile": {
            "name": "Hibeck",
            "id": 6982932,
            "realm": {
              "key": {
                "href": "https://us.api.blizzard.com/data/wow/realm/4648?namespace=dynamic-classic-us"
              },
              "id": 4648,
              "slug": "bloodsail-buccaneers"
            }
          },
          "faction": {
            "type": "ALLIANCE"
          },
          "specialization": {
            "key": {
              "href": "https://us.api.blizzard.com/data/wow/playable-specialization/267?namespace=static-5.5.0_61496-classic-us"
            },
            "id": 267
          }
        },
        {
          "profile": {
            "name": "Fres",
            "id": 12393317,
            "realm": {
              "key": {
                "href": "https://us.api.blizzard.com/data/wow/realm/4648?namespace=dynamic-classic-us"
              },
              "id": 4648,
              "slug": "bloodsail-buccaneers"
            }
          },
          "faction": {
            "type": "ALLIANCE"
          },
          "specialization": {
            "key": {
              "href": "https://us.api.blizzard.com/data/wow/playable-specialization/65?namespace=static-5.5.0_61496-classic-us"
            },
            "id": 65
          }
        },
        {
          "profile": {
            "name": "Kunou",
            "id": 11968765,
            "realm": {
              "key": {
                "href": "https://us.api.blizzard.com/data/wow/realm/4648?namespace=dynamic-classic-us"
              },
              "id": 4648,
              "slug": "bloodsail-buccaneers"
            }
          },
          "faction": {
            "type": "ALLIANCE"
          },
          "specialization": {
            "key": {
              "href": "https://us.api.blizzard.com/data/wow/playable-specialization/73?namespace=static-5.5.0_61496-classic-us"
            },
            "id": 73
          }
        }
      ],
      "mythic_rating": {
        "rating": 30.0
      }
    },
    {
      "ranking": 3,
      "duration": 1904862,
      "completed_timestamp": 1753841239000,
      "keystone_level": 1,
      "members": [
        {
          "profile": {
            "name": "Eyahe",
            "id": 96507906,
            "realm": {
              "key": {
                "href": "https://us.api.blizzard.com/data/wow/realm/4385?namespace=dynamic-classic-us"
              },
              "id": 4385,
              "slug": "pagle"
            }
          },
          "faction": {
            "type": "ALLIANCE"
          },
          "specialization": {
            "key": {
              "href": "https://us.api.blizzard.com/data/wow/playable-specialization/256?namespace=static-5.5.0_61496-classic-us"
            },
            "id": 256
          }
        },
        {
          "profile": {
            "name": "Trowe",
            "id": 96912023,
            "realm": {
              "key": {
                "href": "https://us.api.blizzard.com/data/wow/realm/4385?namespace=dynamic-classic-us"
              },
              "id": 4385,
              "slug": "pagle"
            }
          },
          "faction": {
            "type": "ALLIANCE"
          },
          "specialization": {
            "key": {
              "href": "https://us.api.blizzard.com/data/wow/playable-specialization/63?namespace=static-5.5.0_61496-classic-us"
            },
            "id": 63
          }
        },
        {
          "profile": {
            "name": "Tsu",
            "id": 4925766,
            "realm": {
              "key": {
                "href": "https://us.api.blizzard.com/data/wow/realm/4648?namespace=dynamic-classic-us"
              },
              "id": 4648,
              "slug": "bloodsail-buccaneers"
            }
          },
          "faction": {
            "type": "ALLIANCE"
          },
          "specialization": {
            "key": {
              "href": "https://us.api.blizzard.com/data/wow/playable-specialization/71?namespace=static-5.5.0_61496-classic-us"
            },
            "id": 71
          }
        },
        {
          "profile": {
            "name": "Impmachine",
            "id": 94557314,
            "realm": {
              "key": {
                "href": "https://us.api.blizzard.com/data/wow/realm/4385?namespace=dynamic-classic-us"
              },
              "id": 4385,
              "slug": "pagle"
            }
          },
          "faction": {
            "type": "ALLIANCE"
          },
          "specialization": {
            "key": {
              "href": "https://us.api.blizzard.com/data/wow/playable-specialization/267?namespace=static-5.5.0_61496-classic-us"
            },
            "id": 267
          }
        },
        {
          "profile": {
            "name": "Ederick",
            "id": 89246477,
            "realm": {
              "key": {
                "href": "https://us.api.blizzard.com/data/wow/realm/4385?namespace=dynamic-classic-us"
              },
              "id": 4385,
              "slug": "pagle"
            }
          },
          "faction": {
            "type": "ALLIANCE"
          },
          "specialization": {
            "key": {
              "href": "https://us.api.blizzard.com/data/wow/playable-specialization/66?namespace=static-5.5.0_61496-classic-us"
            },
            "id": 66
          }
        }
      ],
      "mythic_rating": {
        "rating": 28.681194
      }
    }
  ],
  "map_challenge_mode_id": 56,
  "name": {
    "en_US": "Stormstout Brewery",
    "es_MX": "Cervecer\u00eda del Trueno",
    "pt_BR": "Cervejaria Malte do Trov\u00e3o",
    "de_DE": "Die Brauerei Sturmbr\u00e4u",
    "en_GB": "Stormstout Brewery",
    "es_ES": "Cervecer\u00eda del Trueno",
    "fr_FR": "Brasserie Brune d\u2019Orage",
    "it_IT": "Birrificio Triplo Malto",
    "ru_RU": "\u0425\u043c\u0435\u043b\u0435\u0432\u0430\u0440\u043d\u044f \u0411\u0443\u0439\u043d\u044b\u0445 \u041f\u043e\u0440\u0442\u0435\u0440\u043e\u0432",
    "ko_KR": "\uc2a4\ud1b0\uc2a4\ud0c0\uc6b0\ud2b8 \uc591\uc870\uc7a5",
    "zh_TW": "\u98a8\u66b4\u70c8\u9152\u9152\u574a",
    "zh_CN": "\u98ce\u66b4\u70c8\u9152\u917f\u9020\u5382"
  }
}