{"_links":{"self":{"href":"https://eu.api.blizzard.com/data/wow/connected-realm/4477/mythic-leaderboard/76/period/1024?namespace=dynamic-classic-eu"}},"map":{"name":{"en_US":"Scholomance"},"id":1007},"period":1024,"period_start_timestamp":1755057600000,"period_end_timestamp":1755662399000,"connected_realm":{"href":"https://eu.api.blizzard.com/data/wow/connected-realm/4477?namespace=dynamic-classic-eu"},"map_challenge_mode_id":76,"name":{"en_US":"Scholomance"},"leading_groups":[{"ranking":1,"duration":818293,"completed_timestamp":1755090452000,"keystone_level":1,"members":[{"name":"\u0421\u0430\u0431\u043a\u0443\u043b\u044c\u0442","id":59494526,"realm_slug":"flamegor","faction":"HORDE","spec_id":263},{"name":"S\u00e2ccra","id":70355157,"realm_slug":"venoxis","faction":"HORDE","spec_id":64},{"name":"Schleezy","id":73061701,"realm_slug":"venoxis","faction":"HORDE","spec_id":105},{"name":"Megabiffen","id":97741297,"realm_slug":"gehennas","faction":"HORDE","spec_id":66},{"name":"Imamu","id":95901386,"realm_slug":"gehennas","faction":"HORDE","spec_id":252}]},{"ranking":2,"duration":879474,"completed_timestamp":1755161909000,"keystone_level":1,"members":[{"name":"Bobbinho","id":98417173,"realm_slug":"gehennas","faction":"HORDE","spec_id":268},{"name":"Bouncyguzz","id":97555542,"realm_slug":"gehennas","faction":"HORDE","spec_id":270},{"name":"Danklock","id":41151301,"realm_slug":"gehennas","faction":"HORDE","spec_id":267},{"name":"Varehunt","id":96253406,"realm_slug":"venoxis","faction":"HORDE","spec_id":255},{"name":"Devics","id":96408708,"realm_slug":"gehennas","faction":"HORDE","spec_id":64}]},{"ranking":3,"duration":885053,"completed_timestamp":1755115799000,"keystone_level":1,"members":[{"name":"Nohandouts","id":98015583,"realm_slug":"venoxis","faction":"HORDE","spec_id":66},{"name":"Totemschwede","id":63205001,"realm_slug":"venoxis","faction":"HORDE","spec_id":262},{"name":"Senyxx","id":61898723,"realm_slug":"venoxis","faction":"HORDE","spec_id":255},{"name":"Pingaponga","id":103068945,"realm_slug":"lakeshire","faction":"HORDE","spec_id":269},{"name":"W\u00f8rstpl\u00e5\u00fd\u00ebr","id":97628806,"realm_slug":"venoxis","faction":"HORDE","spec_id":256}]},{"ranking":4,"duration":885365,"completed_timestamp":1755104037000,"keystone_level":1,"members":[{"name":"Kabszidklol","id":57277899,"realm_slug":"golemagg","faction":"HORDE","spec_id":250},{"name":"Dacora","id":89185907,"realm_slug":"venoxis","faction":"HORDE","spec_id":65},{"name":"Blitztr\u00f4ll","id":99383356,"realm_slug":"venoxis","faction":"HORDE","spec_id":262},{"name":"Kaelmoth","id":97174695,"realm_slug":"gehennas","faction":"HORDE","spec_id":267},{"name":"Snobbyx","id":96361244,"realm_slug":"venoxis","faction":"HORDE","spec_id":255}]},{"ranking":5,"duration":898809,"completed_timestamp":1755170442000,"keystone_level":1,"members":[{"name":"Pualani","id":15650822,"realm_slug":"venoxis","faction":"HORDE","spec_id":258},{"name":"Jhiro","id":99124481,"realm_slug":"gehennas","faction":"HORDE","spec_id":270},{"name":"Sabish\u00ef","id":98855047,"realm_slug":"gehennas","faction":"HORDE","spec_id":250},{"name":"Isnudk","id":96941639,"realm_slug":"gehennas","faction":"HORDE","spec_id":252},{"name":"Rymdsham","id":92094598,"realm_slug":"gehennas","faction":"HORDE","spec_id":262}]},{"ranking":6,"duration":903663,"completed_timestamp":1755116726000,"keystone_level":1,"members":[{"name":"Pego","id":81376204,"realm_slug":"venoxis","faction":"HORDE","spec_id":261},{"name":"Grakash","id":20486535,"realm_slug":"venoxis","faction":"HORDE","spec_id":255},{"name":"Heeyu","id":81376380,"realm_slug":"venoxis","faction":"HORDE","spec_id":250},{"name":"Zeroquin","id":81376183,"realm_slug":"venoxis","faction":"HORDE","spec_id":267},{"name":"L\u00e8nii","id":93545587,"realm_slug":"venoxis","faction":"HORDE","spec_id":264}]},{"ranking":7,"duration":914324,"completed_timestamp":1755099044000,"keystone_level":1,"members":[{"name":"Raikizhao","id":97249349,"realm_slug":"venoxis","faction":"HORDE","spec_id":270},{"name":"Sunichi","id":97388223,"realm_slug":"gehennas","faction":"HORDE","spec_id":267},{"name":"Lilfizzle","id":92987482,"realm_slug":"gehennas","faction":"HORDE","spec_id":64},{"name":"Petpov","id":104623797,"realm_slug":"golemagg","faction":"HORDE","spec_id":255},{"name":"Chionbrew","id":98690373,"realm_slug":"gehennas","faction":"HORDE","spec_id":268}]},{"ranking":8,"duration":924875,"completed_timestamp":1755103658000,"keystone_level":1,"members":[{"name":"\u00d6korinna","id":97046446,"realm_slug":"venoxis","faction":"HORDE","spec_id":105},{"name":"Hahner","id":62005726,"realm_slug":"venoxis","faction":"HORDE","spec_id":258},{"name":"Mu\u00df","id":62005763,"realm_slug":"venoxis","faction":"HORDE","spec_id":71},{"name":"Kroda","id":61927321,"realm_slug":"venoxis","faction":"HORDE","spec_id":104},{"name":"Githunt","id":62003884,"realm_slug":"venoxis","faction":"HORDE","spec_id":255}]},{"ranking":9,"duration":939611,"completed_timestamp":1755167431000,"keystone_level":1,"members":[{"name":"Johndonut","id":95766088,"realm_slug":"gehennas","faction":"HORDE","spec_id":102},{"name":"R\u00f9mpel","id":97016766,"realm_slug":"venoxis","faction":"HORDE","spec_id":66},{"name":"Lockemup","id":54723194,"realm_slug":"venoxis","faction":"HORDE","spec_id":267},{"name":"Debeljac","id":99064580,"realm_slug":"gehennas","faction":"HORDE","spec_id":270},{"name":"Themistoklhs","id":73702756,"realm_slug":"gehennas","faction":"HORDE","spec_id":253}]},{"ranking":10,"duration":949637,"completed_timestamp":1755107604000,"keystone_level":1,"members":[{"name":"Bigslurp","id":89309063,"realm_slug":"venoxis","faction":"HORDE","spec_id":62},{"name":"Kungfusaku","id":97384214,"realm_slug":"venoxis","faction":"HORDE","spec_id":268},{"name":"Absentminded","id":59910698,"realm_slug":"venoxis","faction":"HORDE","spec_id":71},{"name":"Kuhidian","id":44716519,"realm_slug":"venoxis","faction":"HORDE","spec_id":105},{"name":"Arpakk","id":77617159,"realm_slug":"venoxis","faction":"HORDE","spec_id":261}]},{"ranking":11,"duration":960768,"completed_timestamp":1755194064000,"keystone_level":1,"members":[{"name":"Papypapypapy","id":77107256,"realm_slug":"auberdine","faction":"HORDE","spec_id":263},{"name":"Sixb","id":101819937,"realm_slug":"auberdine","faction":"HORDE","spec_id":105},{"name":"Pytopg","id":72313699,"realm_slug":"venoxis","faction":"HORDE","spec_id":71},{"name":"Ashrakw","id":102891311,"realm_slug":"auberdine","faction":"HORDE","spec_id":73},{"name":"Nyldartz","id":41627787,"realm_slug":"auberdine","faction":"HORDE","spec_id":267}]},{"ranking":12,"duration":983474,"completed_timestamp":1755177302000,"keystone_level":1,"members":[{"name":"Creywar","id":99542242,"realm_slug":"venoxis","faction":"HORDE","spec_id":71},{"name":"S\u00e9ni","id":98334355,"realm_slug":"venoxis","faction":"HORDE","spec_id":105},{"name":"Dktoxx","id":86095533,"realm_slug":"venoxis","faction":"HORDE","spec_id":250},{"name":"Billiegoat","id":96624087,"realm_slug":"gehennas","faction":"HORDE","spec_id":262},{"name":"Smelterboy","id":92996728,"realm_slug":"gehennas","faction":"HORDE","spec_id":267}]},{"ranking":13,"duration":985781,"completed_timestamp":1755187502000,"keystone_level":1,"members":[{"name":"H\u00e1lly","id":103605836,"realm_slug":"golemagg","faction":"HORDE","spec_id":268},{"name":"Last\u00e2r","id":50737762,"realm_slug":"sulfuron","faction":"HORDE","spec_id":255},{"name":"M\u00f4rphe\u00fbs","id":97355391,"realm_slug":"venoxis","faction":"HORDE","spec_id":270},{"name":"Lokeelock","id":72153662,"realm_slug":"golemagg","faction":"HORDE","spec_id":267},{"name":"Yakala","id":72520729,"realm_slug":"golemagg","faction":"HORDE","spec_id":263}]},{"ranking":14,"duration":996993,"completed_timestamp":1755172915000,"keystone_level":1,"members":[{"name":"Aktemium","id":98736490,"realm_slug":"venoxis","faction":"HORDE","spec_id":71},{"name":"Pepechills","id":99132186,"realm_slug":"venoxis","faction":"HORDE","spec_id":250},{"name":"Soifx","id":93034103,"realm_slug":"venoxis","faction":"HORDE","spec_id":105},{"name":"Bigm\u00f2m","id":72411526,"realm_slug":"venoxis","faction":"HORDE","spec_id":64},{"name":"Wishdream","id":90703730,"realm_slug":"venoxis","faction":"HORDE","spec_id":258}]},{"ranking":15,"duration":1062677,"completed_timestamp":1755171938000,"keystone_level":1,"members":[{"name":"Weriano","id":101431273,"realm_slug":"firemaw","faction":"ALLIANCE","spec_id":260},{"name":"Korpensham","id":101583990,"realm_slug":"firemaw","faction":"ALLIANCE","spec_id":262},{"name":"Footstuff","id":101640266,"realm_slug":"firemaw","faction":"ALLIANCE","spec_id":256},{"name":"L\u00f6pesdasilva","id":55803792,"realm_slug":"mirage-raceway","faction":"ALLIANCE","spec_id":104},{"name":"Tooweak","id":99115487,"realm_slug":"venoxis","faction":"ALLIANCE","spec_id":255}]},{"ranking":16,"duration":1073076,"completed_timestamp":1755137195000,"keystone_level":1,"members":[{"name":"Bobbinho","id":98417173,"realm_slug":"gehennas","faction":"HORDE","spec_id":268},{"name":"Melji","id":95222058,"realm_slug":"gehennas","faction":"HORDE","spec_id":264},{"name":"Selym","id":97647036,"realm_slug":"mandokir","faction":"HORDE","spec_id":252},{"name":"Sharptool","id":73958133,"realm_slug":"venoxis","faction":"HORDE","spec_id":251},{"name":"Katawl","id":98005360,"realm_slug":"venoxis","faction":"HORDE","spec_id":267}]},{"ranking":17,"duration":1081356,"completed_timestamp":1755184282000,"keystone_level":1,"members":[{"name":"Arika","id":58617833,"realm_slug":"golemagg","faction":"HORDE","spec_id":250},{"name":"Vsrr","id":83614189,"realm_slug":"gehennas","faction":"HORDE","spec_id":252},{"name":"Donbugisham","id":97902892,"realm_slug":"venoxis","faction":"HORDE","spec_id":264},{"name":"Childishh","id":79862123,"realm_slug":"gehennas","faction":"HORDE","spec_id":255},{"name":"Sunflake","id":61342164,"realm_slug":"venoxis","faction":"HORDE","spec_id":263}]},{"ranking":18,"duration":1138684,"completed_timestamp":1755188816000,"keystone_level":1,"members":[{"name":"Deira","id":90616166,"realm_slug":"venoxis","faction":"HORDE","spec_id":62},{"name":"Radamonk","id":97178647,"realm_slug":"gehennas","faction":"HORDE","spec_id":268},{"name":"Chronosonder","id":95645315,"realm_slug":"gehennas","faction":"HORDE","spec_id":65},{"name":"Pentahazard","id":97148959,"realm_slug":"gehennas","faction":"HORDE","spec_id":267},{"name":"Boldfury","id":104659040,"realm_slug":"auberdine","faction":"HORDE","spec_id":255}]}]}