{"_links":{"self":{"href":"https://us.api.blizzard.com/data/wow/connected-realm/4738/mythic-leaderboard/56/period/1025?namespace=dynamic-classic-us"}},"map":{"name":{"en_US":"Stormstout Brewery"},"id":961},"period":1025,"period_start_timestamp":1755615600000,"period_end_timestamp":1756220399000,"connected_realm":{"href":"https://us.api.blizzard.com/data/wow/connected-realm/4738?namespace=dynamic-classic-us"},"map_challenge_mode_id":56,"name":{"en_US":"Stormstout Brewery"},"leading_groups":[{"ranking":1,"duration":726683,"completed_timestamp":1754099097000,"keystone_level":1,"members":[{"name":"Goodrng","id":58831660,"realm_slug":"faerlina","faction":"HORDE","spec_id":73},{"name":"Yukima","id":58838461,"realm_slug":"faerlina","faction":"HORDE","spec_id":259},{"name":"Sailtotem","id":94915686,"realm_slug":"maladath","faction":"HORDE","spec_id":264},{"name":"Mcwhaa","id":58872778,"realm_slug":"faerlina","faction":"HORDE","spec_id":262},{"name":"Ronst\u00e2r","id":58937665,"realm_slug":"faerlina","faction":"HORDE","spec_id":255}]}]}