{"metadata":{"spec":"shadow","class":"priest","encounter":"p1_raid_three_burst","timestamp":"2025-07-26T00:15:25+10:00","iterations":10000,"encounterDuration":30,"encounterVariation":10,"targetCount":3,"raidBuffs":{"blessingOfMight":true,"bloodlust":true,"darkIntent":true,"leaderOfThePack":true,"legacyOfTheEmperor":true,"moonkinAura":true,"skullBannerCount":2,"stormlashTotemCount":4,"trueshotAura":true,"unholyAura":true}},"results":{"human":{"dps":307339.77824418986,"max":471479.63385596697,"min":226441.8438212591,"stdev":29820.818333599957,"loadout":{"consumables":{"flaskId":76085,"foodId":74650,"potId":76093,"prepotId":76093},"talentsString":"223113","glyphs":{},"equipment":{"items":[{"gems":[76885,76585],"id":87120,"reforging":145},{"id":86976,"reforging":145},{"enchant":4806,"gems":[76642],"id":87123,"reforging":117},{"enchant":4892,"id":90512},{"enchant":4419,"gems":[76633,76633],"id":87122,"reforging":147},{"enchant":4414,"gems":[0],"id":90510,"reforging":117},{"enchant":4433,"gems":[0],"id":87119,"reforging":119,"tinker":4898},{"gems":[76668,76576,76633],"id":86981,"reforging":140},{"enchant":4825,"gems":[76694,76576],"id":87174,"reforging":134},{"enchant":4429,"gems":[76699],"id":86959,"reforging":119},{"id":90511},{"id":86949,"reforging":145},{"id":87065},{"id":87175},{"enchant":4442,"gems":[76585],"id":90513,"reforging":167},{"enchant":4434,"id":89425,"reforging":119}]},"race":"RaceHuman","class":"ClassPriest","profession1":"Engineering","profession2":"Tailoring"}},"dwarf":{"dps":307331.61766560306,"max":471466.7127610983,"min":226435.2222080803,"stdev":29819.69925880805,"loadout":{"consumables":{"flaskId":76085,"foodId":74650,"potId":76093,"prepotId":76093},"talentsString":"223113","glyphs":{},"equipment":{"items":[{"gems":[76885,76585],"id":87120,"reforging":145},{"id":86976,"reforging":145},{"enchant":4806,"gems":[76642],"id":87123,"reforging":117},{"enchant":4892,"id":90512},{"enchant":4419,"gems":[76633,76633],"id":87122,"reforging":147},{"enchant":4414,"gems":[0],"id":90510,"reforging":117},{"enchant":4433,"gems":[0],"id":87119,"reforging":119,"tinker":4898},{"gems":[76668,76576,76633],"id":86981,"reforging":140},{"enchant":4825,"gems":[76694,76576],"id":87174,"reforging":134},{"enchant":4429,"gems":[76699],"id":86959,"reforging":119},{"id":90511},{"id":86949,"reforging":145},{"id":87065},{"id":87175},{"enchant":4442,"gems":[76585],"id":90513,"reforging":167},{"enchant":4434,"id":89425,"reforging":119}]},"race":"RaceDwarf","class":"ClassPriest","profession1":"Engineering","profession2":"Tailoring"}},"night_elf":{"dps":307339.77824418986,"max":471479.63385596697,"min":226441.8438212591,"stdev":29820.818333599957,"loadout":{"consumables":{"flaskId":76085,"foodId":74650,"potId":76093,"prepotId":76093},"talentsString":"223113","glyphs":{},"equipment":{"items":[{"gems":[76885,76585],"id":87120,"reforging":145},{"id":86976,"reforging":145},{"enchant":4806,"gems":[76642],"id":87123,"reforging":117},{"enchant":4892,"id":90512},{"enchant":4419,"gems":[76633,76633],"id":87122,"reforging":147},{"enchant":4414,"gems":[0],"id":90510,"reforging":117},{"enchant":4433,"gems":[0],"id":87119,"reforging":119,"tinker":4898},{"gems":[76668,76576,76633],"id":86981,"reforging":140},{"enchant":4825,"gems":[76694,76576],"id":87174,"reforging":134},{"enchant":4429,"gems":[76699],"id":86959,"reforging":119},{"id":90511},{"id":86949,"reforging":145},{"id":87065},{"id":87175},{"enchant":4442,"gems":[76585],"id":90513,"reforging":167},{"enchant":4434,"id":89425,"reforging":119}]},"race":"RaceNightElf","class":"ClassPriest","profession1":"Engineering","profession2":"Tailoring"}},"gnome":{"dps":307369.98642570915,"max":471518.39714057295,"min":226461.7086607957,"stdev":29822.33809453228,"loadout":{"consumables":{"flaskId":76085,"foodId":74650,"potId":76093,"prepotId":76093},"talentsString":"223113","glyphs":{},"equipment":{"items":[{"gems":[76885,76585],"id":87120,"reforging":145},{"id":86976,"reforging":145},{"enchant":4806,"gems":[76642],"id":87123,"reforging":117},{"enchant":4892,"id":90512},{"enchant":4419,"gems":[76633,76633],"id":87122,"reforging":147},{"enchant":4414,"gems":[0],"id":90510,"reforging":117},{"enchant":4433,"gems":[0],"id":87119,"reforging":119,"tinker":4898},{"gems":[76668,76576,76633],"id":86981,"reforging":140},{"enchant":4825,"gems":[76694,76576],"id":87174,"reforging":134},{"enchant":4429,"gems":[76699],"id":86959,"reforging":119},{"id":90511},{"id":86949,"reforging":145},{"id":87065},{"id":87175},{"enchant":4442,"gems":[76585],"id":90513,"reforging":167},{"enchant":4434,"id":89425,"reforging":119}]},"race":"RaceGnome","class":"ClassPriest","profession1":"Engineering","profession2":"Tailoring"}},"draenei":{"dps":307339.77824418986,"max":471479.63385596697,"min":226441.8438212591,"stdev":29820.818333599957,"loadout":{"consumables":{"flaskId":76085,"foodId":74650,"potId":76093,"prepotId":76093},"talentsString":"223113","glyphs":{},"equipment":{"items":[{"gems":[76885,76585],"id":87120,"reforging":145},{"id":86976,"reforging":145},{"enchant":4806,"gems":[76642],"id":87123,"reforging":117},{"enchant":4892,"id":90512},{"enchant":4419,"gems":[76633,76633],"id":87122,"reforging":147},{"enchant":4414,"gems":[0],"id":90510,"reforging":117},{"enchant":4433,"gems":[0],"id":87119,"reforging":119,"tinker":4898},{"gems":[76668,76576,76633],"id":86981,"reforging":140},{"enchant":4825,"gems":[76694,76576],"id":87174,"reforging":134},{"enchant":4429,"gems":[76699],"id":86959,"reforging":119},{"id":90511},{"id":86949,"reforging":145},{"id":87065},{"id":87175},{"enchant":4442,"gems":[76585],"id":90513,"reforging":167},{"enchant":4434,"id":89425,"reforging":119}]},"race":"RaceDraenei","class":"ClassPriest","profession1":"Engineering","profession2":"Tailoring"}},"worgen":{"dps":310834.6510362057,"max":471427.9494764924,"min":229440.09413302524,"stdev":30214.093459769025,"loadout":{"consumables":{"flaskId":76085,"foodId":74650,"potId":76093,"prepotId":76093},"talentsString":"223113","glyphs":{},"equipment":{"items":[{"gems":[76885,76585],"id":87120,"reforging":145},{"id":86976,"reforging":145},{"enchant":4806,"gems":[76642],"id":87123,"reforging":117},{"enchant":4892,"id":90512},{"enchant":4419,"gems":[76633,76633],"id":87122,"reforging":147},{"enchant":4414,"gems":[0],"id":90510,"reforging":117},{"enchant":4433,"gems":[0],"id":87119,"reforging":119,"tinker":4898},{"gems":[76668,76576,76633],"id":86981,"reforging":140},{"enchant":4825,"gems":[76694,76576],"id":87174,"reforging":134},{"enchant":4429,"gems":[76699],"id":86959,"reforging":119},{"id":90511},{"id":86949,"reforging":145},{"id":87065},{"id":87175},{"enchant":4442,"gems":[76585],"id":90513,"reforging":167},{"enchant":4434,"id":89425,"reforging":119}]},"race":"RaceWorgen","class":"ClassPriest","profession1":"Engineering","profession2":"Tailoring"}},"undead":{"dps":308933.4872708579,"max":444355.8099418523,"min":234626.9249726264,"stdev":29554.168864201518,"loadout":{"consumables":{"flaskId":76085,"foodId":74650,"potId":76093,"prepotId":76093},"talentsString":"223113","glyphs":{},"equipment":{"items":[{"gems":[76885,76585],"id":87120,"reforging":145},{"id":86976,"reforging":145},{"enchant":4806,"gems":[76642],"id":87123,"reforging":117},{"enchant":4892,"id":90512},{"enchant":4419,"gems":[76633,76633],"id":87122,"reforging":147},{"enchant":4414,"gems":[0],"id":90510,"reforging":117},{"enchant":4433,"gems":[0],"id":87119,"reforging":119,"tinker":4898},{"gems":[76668,76576,76633],"id":86981,"reforging":140},{"enchant":4825,"gems":[76694,76576],"id":87174,"reforging":134},{"enchant":4429,"gems":[76699],"id":86959,"reforging":119},{"id":90511},{"id":86949,"reforging":145},{"id":87065},{"id":87175},{"enchant":4442,"gems":[76585],"id":90513,"reforging":167},{"enchant":4434,"id":89425,"reforging":119}]},"race":"RaceUndead","class":"ClassPriest","profession1":"Engineering","profession2":"Tailoring"}},"tauren":{"dps":307300.55299246067,"max":471427.9494764924,"min":226415.3573685437,"stdev":29817.44678277878,"loadout":{"consumables":{"flaskId":76085,"foodId":74650,"potId":76093,"prepotId":76093},"talentsString":"223113","glyphs":{},"equipment":{"items":[{"gems":[76885,76585],"id":87120,"reforging":145},{"id":86976,"reforging":145},{"enchant":4806,"gems":[76642],"id":87123,"reforging":117},{"enchant":4892,"id":90512},{"enchant":4419,"gems":[76633,76633],"id":87122,"reforging":147},{"enchant":4414,"gems":[0],"id":90510,"reforging":117},{"enchant":4433,"gems":[0],"id":87119,"reforging":119,"tinker":4898},{"gems":[76668,76576,76633],"id":86981,"reforging":140},{"enchant":4825,"gems":[76694,76576],"id":87174,"reforging":134},{"enchant":4429,"gems":[76699],"id":86959,"reforging":119},{"id":90511},{"id":86949,"reforging":145},{"id":87065},{"id":87175},{"enchant":4442,"gems":[76585],"id":90513,"reforging":167},{"enchant":4434,"id":89425,"reforging":119}]},"race":"RaceTauren","class":"ClassPriest","profession1":"Engineering","profession2":"Tailoring"}},"troll":{"dps":336810.9587365452,"max":493876.89627002605,"min":248046.1014109223,"stdev":35312.18728998989,"loadout":{"consumables":{"flaskId":76085,"foodId":74650,"potId":76093,"prepotId":76093},"talentsString":"223113","glyphs":{},"equipment":{"items":[{"gems":[76885,76585],"id":87120,"reforging":145},{"id":86976,"reforging":145},{"enchant":4806,"gems":[76642],"id":87123,"reforging":117},{"enchant":4892,"id":90512},{"enchant":4419,"gems":[76633,76633],"id":87122,"reforging":147},{"enchant":4414,"gems":[0],"id":90510,"reforging":117},{"enchant":4433,"gems":[0],"id":87119,"reforging":119,"tinker":4898},{"gems":[76668,76576,76633],"id":86981,"reforging":140},{"enchant":4825,"gems":[76694,76576],"id":87174,"reforging":134},{"enchant":4429,"gems":[76699],"id":86959,"reforging":119},{"id":90511},{"id":86949,"reforging":145},{"id":87065},{"id":87175},{"enchant":4442,"gems":[76585],"id":90513,"reforging":167},{"enchant":4434,"id":89425,"reforging":119}]},"race":"RaceTroll","class":"ClassPriest","profession1":"Engineering","profession2":"Tailoring"}},"blood_elf":{"dps":307369.98642570915,"max":471518.39714057295,"min":226461.7086607957,"stdev":29822.33809453228,"loadout":{"consumables":{"flaskId":76085,"foodId":74650,"potId":76093,"prepotId":76093},"talentsString":"223113","glyphs":{},"equipment":{"items":[{"gems":[76885,76585],"id":87120,"reforging":145},{"id":86976,"reforging":145},{"enchant":4806,"gems":[76642],"id":87123,"reforging":117},{"enchant":4892,"id":90512},{"enchant":4419,"gems":[76633,76633],"id":87122,"reforging":147},{"enchant":4414,"gems":[0],"id":90510,"reforging":117},{"enchant":4433,"gems":[0],"id":87119,"reforging":119,"tinker":4898},{"gems":[76668,76576,76633],"id":86981,"reforging":140},{"enchant":4825,"gems":[76694,76576],"id":87174,"reforging":134},{"enchant":4429,"gems":[76699],"id":86959,"reforging":119},{"id":90511},{"id":86949,"reforging":145},{"id":87065},{"id":87175},{"enchant":4442,"gems":[76585],"id":90513,"reforging":167},{"enchant":4434,"id":89425,"reforging":119}]},"race":"RaceBloodElf","class":"ClassPriest","profession1":"Engineering","profession2":"Tailoring"}},"goblin":{"dps":308752.5051518524,"max":468250.90841088677,"min":229130.59754171353,"stdev":29952.76569904287,"loadout":{"consumables":{"flaskId":76085,"foodId":74650,"potId":76093,"prepotId":76093},"talentsString":"223113","glyphs":{},"equipment":{"items":[{"gems":[76885,76585],"id":87120,"reforging":145},{"id":86976,"reforging":145},{"enchant":4806,"gems":[76642],"id":87123,"reforging":117},{"enchant":4892,"id":90512},{"enchant":4419,"gems":[76633,76633],"id":87122,"reforging":147},{"enchant":4414,"gems":[0],"id":90510,"reforging":117},{"enchant":4433,"gems":[0],"id":87119,"reforging":119,"tinker":4898},{"gems":[76668,76576,76633],"id":86981,"reforging":140},{"enchant":4825,"gems":[76694,76576],"id":87174,"reforging":134},{"enchant":4429,"gems":[76699],"id":86959,"reforging":119},{"id":90511},{"id":86949,"reforging":145},{"id":87065},{"id":87175},{"enchant":4442,"gems":[76585],"id":90513,"reforging":167},{"enchant":4434,"id":89425,"reforging":119}]},"race":"RaceGoblin","class":"ClassPriest","profession1":"Engineering","profession2":"Tailoring"}},"alliance_pandaren":{"dps":310386.49843449664,"max":475343.0412216935,"min":228421.7061617383,"stdev":30100.92483389741,"loadout":{"consumables":{"flaskId":76085,"foodId":74650,"potId":76093,"prepotId":76093},"talentsString":"223113","glyphs":{},"equipment":{"items":[{"gems":[76885,76585],"id":87120,"reforging":145},{"id":86976,"reforging":145},{"enchant":4806,"gems":[76642],"id":87123,"reforging":117},{"enchant":4892,"id":90512},{"enchant":4419,"gems":[76633,76633],"id":87122,"reforging":147},{"enchant":4414,"gems":[0],"id":90510,"reforging":117},{"enchant":4433,"gems":[0],"id":87119,"reforging":119,"tinker":4898},{"gems":[76668,76576,76633],"id":86981,"reforging":140},{"enchant":4825,"gems":[76694,76576],"id":87174,"reforging":134},{"enchant":4429,"gems":[76699],"id":86959,"reforging":119},{"id":90511},{"id":86949,"reforging":145},{"id":87065},{"id":87175},{"enchant":4442,"gems":[76585],"id":90513,"reforging":167},{"enchant":4434,"id":89425,"reforging":119}]},"race":"RaceAlliancePandaren","class":"ClassPriest","profession1":"Engineering","profession2":"Tailoring"}}}}
